LICENSE
MANIFEST.in
README.rst
setup.py
swaggergenerator/__init__.py
swaggergenerator/_version.py
swaggergenerator/paths.py
swaggergenerator/yaml.py
swaggergenerator.egg-info/PKG-INFO
swaggergenerator.egg-info/SOURCES.txt
swaggergenerator.egg-info/dependency_links.txt
swaggergenerator.egg-info/not-zip-safe
swaggergenerator.egg-info/requires.txt
swaggergenerator.egg-info/top_level.txt