Metadata-Version: 1.1
Name: swaggergenerator
Version: 0.0.5
Summary: Automatically generate swagger/OAS schemas from example api interactions.
Home-page: https://github.com/venmo/swaggergenerator
Author: Simon Weber
Author-email: simon@venmo.com
License: MIT
Platform: UNKNOWN
Classifier: Development Status :: 4 - Beta
Classifier: Intended Audience :: Developers
Classifier: License :: OSI Approved :: MIT License
Classifier: Programming Language :: Python
Classifier: Programming Language :: Python :: 2.7
